HEHEHEDB/HEHEHEDB.py
HEHEHEDB/__init__.py
HEHEHEDB-0.1.dist-info/METADATA
HEHEHEDB-0.1.dist-info/WHEEL
HEHEHEDB-0.1.dist-info/license.txt
HEHEHEDB-0.1.dist-info/top_level.txt
HEHEHEDB-0.1.dist-info/RECORD
